ff_iii_luciferin/__init__.py
ff_iii_luciferin/py.typed
ff_iii_luciferin/api/__init__.py
ff_iii_luciferin/api/client.py
ff_iii_luciferin/api/errors.py
ff_iii_luciferin/api/openapi_types.py
ff_iii_luciferin/api/transaction_update.py
ff_iii_luciferin/api/validators.py
ff_iii_luciferin/domain/__init__.py
ff_iii_luciferin/domain/formatters.py
ff_iii_luciferin/domain/models.py
ff_iii_luciferin/mappers/category_mapper.py
ff_iii_luciferin/mappers/transaction_mapper.py
ff_iii_luciferin/mappers/utils.py
ff_iii_luciferin/openapi/__init__.py
ff_iii_luciferin/openapi/openapi_client/models/__init__.py
ff_iii_luciferin/openapi/openapi_client/models/account_array.py
ff_iii_luciferin/openapi/openapi_client/models/account_properties.py
ff_iii_luciferin/openapi/openapi_client/models/account_read.py
ff_iii_luciferin/openapi/openapi_client/models/account_role_property.py
ff_iii_luciferin/openapi/openapi_client/models/account_search_field_filter.py
ff_iii_luciferin/openapi/openapi_client/models/account_single.py
ff_iii_luciferin/openapi/openapi_client/models/account_store.py
ff_iii_luciferin/openapi/openapi_client/models/account_type_filter.py
ff_iii_luciferin/openapi/openapi_client/models/account_type_property.py
ff_iii_luciferin/openapi/openapi_client/models/account_update.py
ff_iii_luciferin/openapi/openapi_client/models/array_entry_with_currency_and_sum.py
ff_iii_luciferin/openapi/openapi_client/models/attachable_type.py
ff_iii_luciferin/openapi/openapi_client/models/attachment_array.py
ff_iii_luciferin/openapi/openapi_client/models/attachment_properties.py
ff_iii_luciferin/openapi/openapi_client/models/attachment_read.py
ff_iii_luciferin/openapi/openapi_client/models/attachment_single.py
ff_iii_luciferin/openapi/openapi_client/models/attachment_store.py
ff_iii_luciferin/openapi/openapi_client/models/attachment_update.py
ff_iii_luciferin/openapi/openapi_client/models/auto_budget_period.py
ff_iii_luciferin/openapi/openapi_client/models/auto_budget_type.py
ff_iii_luciferin-1.0.0b5.dist-info/licenses/LICENSE
ff_iii_luciferin-1.0.0b5.dist-info/METADATA
ff_iii_luciferin-1.0.0b5.dist-info/WHEEL
ff_iii_luciferin-1.0.0b5.dist-info/top_level.txt
ff_iii_luciferin-1.0.0b5.dist-info/RECORD
