Metadata-Version: 2.4
Name: ff-iii-luciferin
Version: 1.0.0b5
Summary: A Firefly III enrichment engine that makes your data glow
Author-email: wini83 <rico.gotti210@gmail.com>
License: MIT
Project-URL: Homepage, https://github.com/wini83/ff-iii-luciferin
Project-URL: Repository, https://github.com/wini83/ff-iii-luciferin
Project-URL: Issues, https://github.com/wini83/ff-iii-luciferin/issues
Project-URL: Changelog, https://github.com/wini83/ff-iii-luciferin/blob/main/CHANGELOG.md
Keywords: firefly-iii,finance,enrichment,transactions,api
Classifier: License :: OSI Approved :: MIT License
Classifier: Programming Language :: Python :: 3
Classifier: Programming Language :: Python :: 3.12
Classifier: Operating System :: OS Independent
Requires-Python: >=3.12
License-File: LICENSE
Requires-Dist: aenum>=3.1.16
Requires-Dist: httpx
Dynamic: license-file
